dialog_workflow/Act.py
dialog_workflow/Constants.py
dialog_workflow/DialogWorkflow.py
dialog_workflow/TablesAsObjects.py
dialog_workflow/__init__.py
dialog_workflow/utils.py
dialog_workflow-0.0.71.dist-info/METADATA
dialog_workflow-0.0.71.dist-info/WHEEL
dialog_workflow-0.0.71.dist-info/top_level.txt
dialog_workflow-0.0.71.dist-info/RECORD
