Metadata-Version: 2.1
Name: dialog-workflow
Version: 0.0.71
Summary: PyPI Package for dialog workflow
Home-page: https://github.com/javatechy/dokr
Author: Circles
Author-email: info@circle.life
Classifier: Programming Language :: Python :: 3
Classifier: License :: Other/Proprietary License
Classifier: Operating System :: OS Independent
Requires-Dist: python-dotenv >=1.0.0
Requires-Dist: variable-local >=0.0.43
